kitmin/__init__.py
kitmin/kitmin.py
kitmin-0.1.0.dist-info/METADATA
kitmin-0.1.0.dist-info/WHEEL
kitmin-0.1.0.dist-info/top_level.txt
kitmin-0.1.0.dist-info/RECORD
