Metadata-Version: 2.1
Name: kitmin
Version: 0.1.0
Summary: Webkit Webmin Gui
Home-page: https://gitlab.com/onix-os/applications/webkit-webmin
Author: Oytun OZDEMIR
Author-email: info@oytun.org
License: BSD 2-clause
Platform: UNKNOWN
Classifier: Development Status :: 1 - Planning
Classifier: Intended Audience :: Science/Research
Classifier: License :: OSI Approved :: BSD License
Classifier: Operating System :: POSIX :: Linux
Classifier: Programming Language :: Python :: 2
Classifier: Programming Language :: Python :: 2.7
Classifier: Programming Language :: Python :: 3
Classifier: Programming Language :: Python :: 3.4
Classifier: Programming Language :: Python :: 3.5
Requires-Dist: pywebview
